AUTHORS.txt
CHANGES.txt
LICENSE.txt
MANIFEST.in
README.rst
setup.py
genepidgin/__init__.py
genepidgin/cleaner.py
genepidgin/cmdline.py
genepidgin/distance.py
genepidgin/evaluator.py
genepidgin/filters.py
genepidgin/scorer.py
genepidgin/selector.py
genepidgin/stemmer.py
genepidgin/util.py
genepidgin.egg-info/PKG-INFO
genepidgin.egg-info/SOURCES.txt
genepidgin.egg-info/dependency_links.txt
genepidgin.egg-info/entry_points.txt
genepidgin.egg-info/not-zip-safe
genepidgin.egg-info/requires.txt
genepidgin.egg-info/top_level.txt
genepidgin/test/__init__.py
genepidgin/test/cleaner_test.py
genepidgin/test/cli_test.py
genepidgin/test/distance_test.py
genepidgin/test/scorer_test.py
genepidgin/test/selector_test.py
genepidgin/test/util_test.py
genepidgin/test/data/dest1Alone.pidginb
genepidgin/test/data/dest1Alone.pidginh
genepidgin/test/data/empty.pidginb
genepidgin/test/data/empty.pidginh
genepidgin/test/data/incorrect.extension
genepidgin/test/data/kegg.names.txt
genepidgin/test/data/scorequery1.txt
genepidgin/test/data/scorequery2.txt
genepidgin/test/data/scoreref.txt
genepidgin/test/data/testCleanupNames.txt
genepidgin/test/data/testCleanupNames_expected.txt
genepidgin/test/data/testDistanceIn.txt
genepidgin/test/data/testDistanceOut.txt
genepidgin/test/data/testSimpleNamesFileReader.txt
genepidgin/test/data/testorg.kegg.blastm8