Metadata-Version: 1.0
Name: genepidgin
Version: 1.1.0
Summary: gene naming utility belt
Home-page: https://www.github.com/clinthowarth/genepidgin
Author: Clint Howarth
Author-email: clint.howarth@gmail.com
License: BSD
Keywords: bioinformatics homology-naming gene-naming
Platform: UNKNOWN
Classifier: Development Status :: 4 - Beta
Classifier: License :: OSI Approved :: BSD License
Classifier: Programming Language :: Python :: 2
